quartier_intelligence/__init__.py
quartier_intelligence-0.0.6.dist-info/licenses/LICENSE
quartier_intelligence-0.0.6.dist-info/METADATA
quartier_intelligence-0.0.6.dist-info/WHEEL
quartier_intelligence-0.0.6.dist-info/top_level.txt
quartier_intelligence-0.0.6.dist-info/RECORD
